LICENSE.txt
MANIFEST.in
README.rst
setup.py
tox.ini
docs/changelog.txt
docs/index.txt
txTemplate.egg-info/PKG-INFO
txTemplate.egg-info/SOURCES.txt
txTemplate.egg-info/dependency_links.txt
txTemplate.egg-info/requires.txt
txTemplate.egg-info/top_level.txt
txtemplate/__init__.py
txtemplate/clearsilver.py
txtemplate/itemplate.py
txtemplate/templates.py
txtemplate/test/__init__.py
txtemplate/test/test_adapters.py
txtemplate/test/test_clearsilver.py
txtemplate/test/test_templates.py