Metadata-Version: 1.1
Name: txTemplate
Version: 1.0.3
Summary: Twisted Adapters for Templating Engines
Home-page: http://github.com/steder/txtemplate
Author: Mike Steder
Author-email: steder@gmail.com
License: MIT
Platform: UNKNOWN
Classifier: Development Status :: 3 - Alpha
Classifier: Intended Audience :: Developers
Classifier: License :: OSI Approved :: MIT License
Classifier: Programming Language :: Python
Classifier: Programming Language :: Python :: 2.6
Classifier: Programming Language :: Python :: 2.7
